long_s/__init__.py
long_s/_convert.py
long_s/_german_conversion.py
long_s/_german_lists.py
long_s/_simple_conversions.py
long_s/_split_words.py
long_s/german-lists/processed/1-exact-matches.json
long_s/german-lists/processed/1-long-s-names.json
long_s/german-lists/processed/2-forced-overwrites.json
long_s/german-lists/processed/3-end-patterns.json
long_s/german-lists/processed/4-omnipresent-patterns.json
long_s/german-lists/processed/5-start-patterns.json
long_s/german-lists/processed/6-postprocess-patterns.json
long_s/german-lists/raw/1-exact-matches.json
long_s/german-lists/raw/1-long-s-names.json
long_s/german-lists/raw/2-forced-overwrites.json
long_s/german-lists/raw/3-end-patterns.json
long_s/german-lists/raw/4-omnipresent-patterns.json
long_s/german-lists/raw/5-start-patterns.json
long_s/german-lists/raw/6-postprocess-patterns.json
long_s-1.0.33.dist-info/LICENSE
long_s-1.0.33.dist-info/METADATA
long_s-1.0.33.dist-info/WHEEL
long_s-1.0.33.dist-info/top_level.txt
long_s-1.0.33.dist-info/RECORD
