Metadata-Version: 2.1
Name: long_s
Version: 1.0.33
Summary: This Python tool accurately inserts the historical long S character ( ſ ) back into the given text to make it appear as if it were written before the 20th century. English, French, German, Spanish and Italian are supported.
Home-page: https://github.com/travisgk/py-long-s/tree/main
Author: TravisGK
Author-email: githubtravisgk@gmail.com
Classifier: Programming Language :: Python :: 3
Classifier: License :: OSI Approved :: MIT License
Classifier: Operating System :: OS Independent
Requires-Python: >=3.6
License-File: LICENSE
Requires-Dist: numpy>=1.21.0
Requires-Dist: python-docx>=1.1.0
Requires-Dist: odfpy>=1.4.0
Requires-Dist: unidecode>=1.3.0
